google/cloud/binaryauthorization/__init__.py
google/cloud/binaryauthorization/gapic_version.py
google/cloud/binaryauthorization/py.typed
google/cloud/binaryauthorization_v1/__init__.py
google/cloud/binaryauthorization_v1/gapic_metadata.json
google/cloud/binaryauthorization_v1/gapic_version.py
google/cloud/binaryauthorization_v1/py.typed
google/cloud/binaryauthorization_v1/services/__init__.py
google/cloud/binaryauthorization_v1/services/binauthz_management_service_v1/__init__.py
google/cloud/binaryauthorization_v1/services/binauthz_management_service_v1/async_client.py
google/cloud/binaryauthorization_v1/services/binauthz_management_service_v1/client.py
google/cloud/binaryauthorization_v1/services/binauthz_management_service_v1/pagers.py
google/cloud/binaryauthorization_v1/services/binauthz_management_service_v1/transports/__init__.py
google/cloud/binaryauthorization_v1/services/binauthz_management_service_v1/transports/base.py
google/cloud/binaryauthorization_v1/services/binauthz_management_service_v1/transports/grpc.py
google/cloud/binaryauthorization_v1/services/binauthz_management_service_v1/transports/grpc_asyncio.py
google/cloud/binaryauthorization_v1/services/binauthz_management_service_v1/transports/rest.py
google/cloud/binaryauthorization_v1/services/binauthz_management_service_v1/transports/rest_base.py
google/cloud/binaryauthorization_v1/services/system_policy_v1/__init__.py
google/cloud/binaryauthorization_v1/services/system_policy_v1/async_client.py
google/cloud/binaryauthorization_v1/services/system_policy_v1/client.py
google/cloud/binaryauthorization_v1/services/system_policy_v1/transports/__init__.py
google/cloud/binaryauthorization_v1/services/system_policy_v1/transports/base.py
google/cloud/binaryauthorization_v1/services/system_policy_v1/transports/grpc.py
google/cloud/binaryauthorization_v1/services/system_policy_v1/transports/grpc_asyncio.py
google/cloud/binaryauthorization_v1/services/system_policy_v1/transports/rest.py
google_cloud_binary_authorization-1.15.0.dist-info/licenses/LICENSE
google_cloud_binary_authorization-1.15.0.dist-info/METADATA
google_cloud_binary_authorization-1.15.0.dist-info/WHEEL
google_cloud_binary_authorization-1.15.0.dist-info/top_level.txt
google_cloud_binary_authorization-1.15.0.dist-info/RECORD
